README.rst
setup.py
asyncio_redis_ha/__init__.py
asyncio_redis_ha/connection.py
asyncio_redis_ha/log.py
asyncio_redis_ha/manager.py
asyncio_redis_ha/protocol.py
asyncio_redis_ha/replies.py
asyncio_redis_ha.egg-info/PKG-INFO
asyncio_redis_ha.egg-info/SOURCES.txt
asyncio_redis_ha.egg-info/dependency_links.txt
asyncio_redis_ha.egg-info/requires.txt
asyncio_redis_ha.egg-info/top_level.txt