Metadata-Version: 1.1
Name: asyncio-redis-ha
Version: 0.1.1
Summary: Redis/Sentinel High Availability package for asyncio-redis
Home-page: https://github.com/dikderoy/asyncio_redis_ha
Author: Roman Bulgakov
Author-email: UNKNOWN
License: MIT
Keywords: redis sentinel high-availability client asyncio
Platform: UNKNOWN
Classifier: Development Status :: 3 - Alpha
Classifier: Intended Audience :: Developers
Classifier: Topic :: Software Development :: Libraries :: Python Modules
Classifier: Topic :: Database :: Front-Ends
Classifier: License :: OSI Approved :: MIT License
Classifier: Programming Language :: Python :: 3 :: Only
Classifier: Programming Language :: Python :: 3.3
Classifier: Programming Language :: Python :: 3.4
Classifier: Programming Language :: Python :: 3.5
